fxq/gcp/__init__.py
fxq/gcp/cloud_func.py
fxq/gcp/datastore.py
fxq/gcp/pub_sub.py
fxq_gcp_commons-1.3.3.dist-info/METADATA
fxq_gcp_commons-1.3.3.dist-info/WHEEL
fxq_gcp_commons-1.3.3.dist-info/top_level.txt
fxq_gcp_commons-1.3.3.dist-info/RECORD
