Metadata-Version: 2.1
Name: fxq-gcp-commons
Version: 1.3.3
Summary: UNKNOWN
Home-page: https://bitbucket.org/fxqlabs/fxq-gcp-commons/
Author: Jonathan Turnock
Author-email: jonathan.turnock@outlook.com
License: MIT
Platform: UNKNOWN
Requires-Dist: grpcio
Requires-Dist: Flask
Requires-Dist: google-cloud-datastore
Requires-Dist: google-cloud-pubsub
